pathogena/__init__.py
pathogena/batch_upload_apis.py
pathogena/cli.py
pathogena/constants.py
pathogena/create_upload_csv.py
pathogena/errors.py
pathogena/lib.py
pathogena/log_utils.py
pathogena/models.py
pathogena/upload_utils.py
pathogena/util.py
pathogena-2.2.2.dist-info/entry_points.txt
pathogena-2.2.2.dist-info/licenses/LICENSE
pathogena-2.2.2.dist-info/WHEEL
pathogena-2.2.2.dist-info/METADATA
pathogena-2.2.2.dist-info/RECORD
