Metadata-Version: 2.4
Name: pathogena
Version: 2.2.2
Summary: The command line and Python client for EIT Pathogena.
Keywords: pathogen,pathogena,eit
Author-email: EIT Pathogena Devs <pathogena.support@eit.org>
Maintainer-email: EIT Pathogena Devs <pathogena.support@eit.org>
Requires-Python: >=3.10
License-File: LICENSE
Requires-Dist: httpx>=0.27.0
Requires-Dist: packaging>=23.2
Requires-Dist: platformdirs>=3.9.1,<=4.2.0
Requires-Dist: tqdm==4.66.3
Requires-Dist: pydantic>=2.6.2,<3
Requires-Dist: tenacity==8.2.3
Requires-Dist: click>=8.1.7
Requires-Dist: python-dotenv>=1.0
Requires-Dist: flit>=3.9.0 ; extra == "dev"
Requires-Dist: pre-commit>=4.0.1 ; extra == "dev"
Requires-Dist: pytest>=8.3.3 ; extra == "dev"
Requires-Dist: ruff>=0.7.1 ; extra == "dev"
Requires-Dist: pytest-mock>=3.14.0 ; extra == "dev"
Provides-Extra: dev
